config/README.md
config/__init__.py
config/loader.py
config/pipeline.yaml
config/settings.py
integrations/README_MEMG_GUIDE.md
integrations/mcp/README.md
integrations/mcp/rebrain.yaml
integrations/mcp/result_cleaner.py
integrations/mcp/server.py
rebrain/__init__.py
rebrain/cli.py
rebrain/config/user_config.py
rebrain/core/__init__.py
rebrain/core/genai_client.py
rebrain/ingestion/__init__.py
rebrain/ingestion/models.py
rebrain/ingestion/parsers.py
rebrain/operations/__init__.py
rebrain/operations/clusterer.py
rebrain/operations/embedder.py
rebrain/operations/filter.py
rebrain/operations/relationship_analyzer.py
rebrain/operations/synthesizer.py
rebrain/persona/__init__.py
rebrain/persona/formatters.py
rebrain/prompts/__init__.py
rebrain/prompts/prompt_loader.py
rebrain/prompts/templates/cognition_synthesis.yaml
rebrain/prompts/templates/learning_cognition_relationship.yaml
rebrain/prompts/templates/learning_synthesis.yaml
rebrain/prompts/templates/observation_extraction.yaml
rebrain/prompts/templates/persona_synthesis.yaml
rebrain/schemas/__init__.py
rebrain/schemas/cognition.py
rebrain/schemas/learning.py
rebrain/schemas/observation.py
rebrain/schemas/persona.py
rebrain/schemas/relationship.py
rebrain/utils/__init__.py
rebrain/utils/text_cleaning.py
rebrain-0.1.7.dist-info/licenses/LICENSE
scripts/format.sh
scripts/lint.sh
scripts/load_memg.py
scripts/analysis/analyze_conversation_lengths.py
scripts/analysis/analyze_distribution.py
scripts/analysis/analyze_token_hierarchy.py
scripts/export/convert_to_csv.py
scripts/export/convert_to_markdown.py
scripts/export/export_cognitions_csv.py
scripts/export/export_learnings_csv.py
scripts/pipeline/01_transform_filter.py
scripts/pipeline/02_extract_cluster_observations.py
scripts/pipeline/03_synthesize_cluster_learnings.py
scripts/pipeline/04_synthesize_cognitions.py
scripts/pipeline/05_build_persona.py
scripts/pipeline/06_analyze_relationships.py
scripts/pipeline/README.md
scripts/pipeline/cli.sh
rebrain-0.1.7.dist-info/METADATA
rebrain-0.1.7.dist-info/WHEEL
rebrain-0.1.7.dist-info/entry_points.txt
rebrain-0.1.7.dist-info/top_level.txt
rebrain-0.1.7.dist-info/RECORD
