Metadata-Version: 2.4
Name: rebrain
Version: 0.1.7
Summary: Transform chat history into structured, navigable memory graphs
Author-email: Yasin Salimibeni <sbyasin@gmail.com>
License: MIT
Project-URL: Homepage, https://github.com/yasinsb/rebrain
Project-URL: Repository, https://github.com/yasinsb/rebrain
Project-URL: Issues, https://github.com/yasinsb/rebrain/issues
Keywords: memory,ai,graph,vector-db,persona,cognition
Classifier: Development Status :: 3 - Alpha
Classifier: Intended Audience :: Developers
Classifier: License :: OSI Approved :: MIT License
Classifier: Programming Language :: Python :: 3
Classifier: Programming Language :: Python :: 3.10
Classifier: Programming Language :: Python :: 3.11
Classifier: Programming Language :: Python :: 3.12
Requires-Python: >=3.10
License-File: LICENSE
Requires-Dist: python-dotenv>=1.0.0
Requires-Dist: pydantic>=2.0.0
Requires-Dist: pydantic-settings>=2.0.0
Requires-Dist: pyyaml>=6.0.0
Requires-Dist: google-genai>=1.42.0
Requires-Dist: google-adk>=1.16.0
Requires-Dist: memg-core>=0.7.5
Requires-Dist: fastmcp>=2.11.3
Requires-Dist: numpy>=1.24.0
Requires-Dist: scikit-learn>=1.3.0
Requires-Dist: hdbscan>=0.8.0
Requires-Dist: scipy>=1.14.0
Requires-Dist: tiktoken>=0.5.0
Requires-Dist: pandas>=2.0.0
Provides-Extra: dev
Requires-Dist: jupyter>=1.0.0; extra == "dev"
Requires-Dist: jupyterlab>=4.0.0; extra == "dev"
Requires-Dist: ipykernel>=6.25.0; extra == "dev"
Requires-Dist: ipywidgets>=8.1.0; extra == "dev"
Requires-Dist: pytest>=7.4.0; extra == "dev"
Requires-Dist: pytest-cov>=4.1.0; extra == "dev"
Requires-Dist: pytest-asyncio>=0.21.0; extra == "dev"
Requires-Dist: black>=23.7.0; extra == "dev"
Requires-Dist: ruff>=0.6.0; extra == "dev"
Requires-Dist: pylint>=3.0.0; extra == "dev"
Requires-Dist: isort>=5.12.0; extra == "dev"
Requires-Dist: mypy>=1.5.0; extra == "dev"
Requires-Dist: ipdb>=0.13.0; extra == "dev"
Requires-Dist: rich>=13.5.0; extra == "dev"
Dynamic: license-file
